aiohttp_jinja2/__init__.py
aiohttp_jinja2/helpers.py
aiohttp_jinja2/py.typed
aiohttp_jinja2/typedefs.py
aiohttp_jinja2-1.5.1.dist-info/LICENSE
aiohttp_jinja2-1.5.1.dist-info/METADATA
aiohttp_jinja2-1.5.1.dist-info/WHEEL
aiohttp_jinja2-1.5.1.dist-info/top_level.txt
aiohttp_jinja2-1.5.1.dist-info/RECORD
