Metadata-Version: 2.1
Name: aiohttp-jinja2
Version: 1.5.1
Summary: jinja2 template renderer for aiohttp.web (http server for asyncio)
Home-page: https://github.com/aio-libs/aiohttp_jinja2/
Author: Andrew Svetlov
Author-email: andrew.svetlov@gmail.com
License: Apache 2
Classifier: License :: OSI Approved :: Apache Software License
Classifier: Intended Audience :: Developers
Classifier: Programming Language :: Python
Classifier: Programming Language :: Python :: 3
Classifier: Programming Language :: Python :: 3.7
Classifier: Programming Language :: Python :: 3.8
Classifier: Programming Language :: Python :: 3.9
Classifier: Programming Language :: Python :: 3.10
Classifier: Programming Language :: Python :: 3.11
Classifier: Development Status :: 5 - Production/Stable
Classifier: Topic :: Internet :: WWW/HTTP
Classifier: Framework :: AsyncIO
Classifier: Framework :: aiohttp
Requires-Python: >=3.7
License-File: LICENSE
